CHANGES.rst
COPYING
MANIFEST.in
Makefile
README.rst
bootstrap-buildout.py
bootstrap-virtualenv.in
bootstrap-virtualenv.py
buildout.cfg
ez_setup.py
requirements-dev.in
requirements-dev.txt
requirements-test.in
requirements.in
requirements.txt
setup.cfg
setup.py
tox.ini
docs/Makefile
docs/changelogs.rst
docs/conf.py
docs/index.rst
docs/intro.rst
docs/make.bat
docs/locale/en/LC_MESSAGES/changelogs.po
docs/locale/en/LC_MESSAGES/cli.po
docs/locale/en/LC_MESSAGES/index.po
docs/locale/en/LC_MESSAGES/intro.po
docs/locale/ko/LC_MESSAGES/changelogs.po
docs/locale/ko/LC_MESSAGES/cli.po
docs/locale/ko/LC_MESSAGES/index.po
docs/locale/ko/LC_MESSAGES/intro.po
docs/locale/pot/changelogs.pot
docs/locale/pot/cli.pot
docs/locale/pot/index.pot
docs/locale/pot/intro.pot
docs/static/empty.css
mete0r.recipe.nodejs.egg-info/PKG-INFO
mete0r.recipe.nodejs.egg-info/SOURCES.txt
mete0r.recipe.nodejs.egg-info/dependency_links.txt
mete0r.recipe.nodejs.egg-info/entry_points.txt
mete0r.recipe.nodejs.egg-info/not-zip-safe
mete0r.recipe.nodejs.egg-info/requires.txt
mete0r.recipe.nodejs.egg-info/top_level.txt
mete0r_recipe_nodejs/__init__.py
mete0r_recipe_nodejs/recipe/__init__.py
mete0r_recipe_nodejs/tests/__init__.py
mete0r_recipe_nodejs/tests/test_app.py