Metadata-Version: 1.1
Name: mete0r.recipe.nodejs
Version: 0.0.0
Summary: a buildout recipe to install node.js
Home-page: https://github.com/mete0r/mete0r.recipe.nodejs
Author: mete0r
Author-email: mete0r@sarangbang.or.kr
License: GNU Affero General Public License v3 or later (AGPLv3+)
Keywords: buildout,nodejs
Platform: UNKNOWN
Classifier: Development Status :: 1 - Planning
Classifier: License :: OSI Approved :: GNU Affero General Public License v3 or later (AGPLv3+)
Classifier: Programming Language :: Python :: 2.7
